hiddenlayer/__init__.py
hiddenlayer/_base_client.py
hiddenlayer/_client.py
hiddenlayer/_compat.py
hiddenlayer/_constants.py
hiddenlayer/_exceptions.py
hiddenlayer/_files.py
hiddenlayer/_models.py
hiddenlayer/_oauth2.py
hiddenlayer/_qs.py
hiddenlayer/_resource.py
hiddenlayer/_response.py
hiddenlayer/_streaming.py
hiddenlayer/_types.py
hiddenlayer/_version.py
hiddenlayer/pagination.py
hiddenlayer/py.typed
hiddenlayer/_utils/__init__.py
hiddenlayer/_utils/_compat.py
hiddenlayer/_utils/_datetime_parse.py
hiddenlayer/_utils/_logs.py
hiddenlayer/_utils/_proxy.py
hiddenlayer/_utils/_reflection.py
hiddenlayer/_utils/_resources_proxy.py
hiddenlayer/_utils/_streams.py
hiddenlayer/_utils/_sync.py
hiddenlayer/_utils/_transform.py
hiddenlayer/_utils/_typing.py
hiddenlayer/_utils/_utils.py
hiddenlayer/lib/.keep
hiddenlayer/lib/__init__.py
hiddenlayer/lib/community_scan.py
hiddenlayer/lib/model_scan.py
hiddenlayer/lib/scan_utils.py
hiddenlayer/resources/__init__.py
hiddenlayer/resources/interactions.py
hiddenlayer/resources/prompt_analyzer.py
hiddenlayer/resources/sensors.py
hiddenlayer/resources/models/__init__.py
hiddenlayer/resources/models/cards.py
hiddenlayer/resources/models/models.py
hiddenlayer/resources/scans/__init__.py
hiddenlayer/resources/scans/jobs.py
hiddenlayer/resources/scans/results.py
hiddenlayer/resources/scans/scans.py
hiddenlayer/resources/scans/upload/__init__.py
hiddenlayer/resources/scans/upload/file.py
hiddenlayer/resources/scans/upload/upload.py
hiddenlayer/types/__init__.py
hiddenlayer/types/interaction_analyze_params.py
hiddenlayer/types/interaction_analyze_response.py
hiddenlayer/types/model_retrieve_response.py
hiddenlayer/types/prompt_analyzer_create_params.py
hiddenlayer/types/prompt_analyzer_create_response.py
hiddenlayer/types/sensor_create_params.py
hiddenlayer/types/sensor_create_response.py
hiddenlayer/types/sensor_query_params.py
hiddenlayer/types/sensor_query_response.py
hiddenlayer/types/sensor_retrieve_response.py
hiddenlayer_sdk-3.2.2.dist-info/METADATA
hiddenlayer_sdk-3.2.2.dist-info/WHEEL
hiddenlayer_sdk-3.2.2.dist-info/licenses/LICENSE
hiddenlayer_sdk-3.2.2.dist-info/RECORD
